LICENSE
README.md
setup.py
qakits/__init__.py
qakits.egg-info/PKG-INFO
qakits.egg-info/SOURCES.txt
qakits.egg-info/dependency_links.txt
qakits.egg-info/entry_points.txt
qakits.egg-info/requires.txt
qakits.egg-info/top_level.txt
qakits/bin/__init__.py
qakits/bin/energy2all.py
qakits/plot/__init__.py
qakits/plot/plotOB.py
qakits/q_epsilon/__init__.py
qakits/q_epsilon/epsilon.py
qakits/vars/__init__.py
qakits/vars/units.py